fyers_apiv3/__init__.py
fyers_apiv3/fyersModel.py
fyers_apiv3/fyers_logger.py
fyers_apiv3/FyersWebsocket/__init__.py
fyers_apiv3/FyersWebsocket/data_ws.py
fyers_apiv3/FyersWebsocket/defines.py
fyers_apiv3/FyersWebsocket/map.json
fyers_apiv3/FyersWebsocket/order_ws.py
fyers_apiv3_beta-1.0.0.dist-info/LICENSE.txt
fyers_apiv3_beta-1.0.0.dist-info/METADATA
fyers_apiv3_beta-1.0.0.dist-info/WHEEL
fyers_apiv3_beta-1.0.0.dist-info/top_level.txt
fyers_apiv3_beta-1.0.0.dist-info/RECORD
